xltpl/__init__.py
xltpl/base.py
xltpl/basex.py
xltpl/cellcontext.py
xltpl/celltag.py
xltpl/config.py
xltpl/filters.py
xltpl/image.py
xltpl/jinja.py
xltpl/merger.py
xltpl/mergerx.py
xltpl/misc.py
xltpl/nodemap.py
xltpl/patchx.py
xltpl/richtexthandler.py
xltpl/sheetresource.py
xltpl/utils.py
xltpl/writer.py
xltpl/writermixin.py
xltpl/writerx.py
xltpl/xlext.py
xltpl/xlnode.py
xltpl/ynext.py
xltpl-0.21.dist-info/LICENSE
xltpl-0.21.dist-info/METADATA
xltpl-0.21.dist-info/WHEEL
xltpl-0.21.dist-info/top_level.txt
xltpl-0.21.dist-info/RECORD
