Metadata-Version: 2.1
Name: xltpl
Version: 0.21
Summary: A python module to generate xls/x files from a xls/x template
Home-page: https://github.com/zhangyu836/xltpl
Author: Zhang Yu
Author-email: zhangyu836@gmail.com
License: MIT
Keywords: Excel,xls,xlsx,spreadsheet,workbook,template
Platform: Any platform 
